example/__init__.py
example/example.py
name_conversion/__init__.py
name_conversion/converter.py
name_conversion/enums.py
name_conversion/rules/rules.json
tests/__init__.py
tests/simple.py
Name_conversion-3.0.0.dist-info/LICENSE
Name_conversion-3.0.0.dist-info/METADATA
Name_conversion-3.0.0.dist-info/WHEEL
Name_conversion-3.0.0.dist-info/top_level.txt
Name_conversion-3.0.0.dist-info/RECORD
